pyautoguide/__init__.py
pyautoguide/_types.py
pyautoguide/actions.py
pyautoguide/box_array.py
pyautoguide/box_array.pyi
pyautoguide/constants.py
pyautoguide/ocr.py
pyautoguide/ocr_config.yaml
pyautoguide/references.py
pyautoguide/scene.py
pyautoguide/session.py
pyautoguide/shapes.py
pyautoguide/utils.py
pyautoguide/workflow.py
pyautoguide-0.4.3.dist-info/METADATA
pyautoguide-0.4.3.dist-info/WHEEL
pyautoguide-0.4.3.dist-info/entry_points.txt
pyautoguide-0.4.3.dist-info/licenses/LICENSE
pyautoguide-0.4.3.dist-info/RECORD
