Metadata-Version: 2.4
Name: pyautoguide
Version: 0.4.3
Summary: Advance GUI automation
Author-email: pritam-dey3 <pritam.pritamdey.984@gmail.com>
License-File: LICENSE
Requires-Python: >=3.13
Requires-Dist: graphviz>=0.21
Requires-Dist: networkx>=3.5
Requires-Dist: opencv-python-headless>=4.12.0.88
Requires-Dist: pillow>=11.3.0
Requires-Dist: pyautogui>=0.9.54
Requires-Dist: python-statemachine[diagrams]
Requires-Dist: transitions>=0.9.3
Provides-Extra: ocr
Requires-Dist: onnxruntime>=1.22.0; extra == 'ocr'
Requires-Dist: rapidocr>=3.2.0; extra == 'ocr'
